{"DocumentConnection":{"type":"DocumentConnection","resolveType":"multiCollectionDocumentList","collections":["page","post","abtest"]},"Node":{"type":"Node","resolveType":"nodeDocument"},"DocumentNode":{"type":"DocumentNode","resolveType":"multiCollectionDocument","createDocument":"create","updateDocument":"update"},"PageBlocksFeaturesItems":{"type":"PageBlocksFeaturesItems","resolveType":"unionData","typeMap":{"feature":"PageBlocksFeaturesItemsFeature"}},"PageBlocksShowcaseItems":{"type":"PageBlocksShowcaseItems","resolveType":"unionData","typeMap":{"project":"PageBlocksShowcaseItemsProject"}},"PageBlocks":{"type":"PageBlocks","resolveType":"unionData","typeMap":{"hero":"PageBlocksHero","features":"PageBlocksFeatures","flying":"PageBlocksFlying","pricing":"PageBlocksPricing","faq":"PageBlocksFaq","content":"PageBlocksContent","showcase":"PageBlocksShowcase","columns":"PageBlocksColumns"}},"Page":{"type":"Page","resolveType":"collectionDocument","collection":"page","createPage":"create","updatePage":"update"},"PageConnection":{"type":"PageConnection","resolveType":"collectionDocumentList","collection":"page"},"PostPrev":{"type":"PostPrev","resolveType":"multiCollectionDocument","createDocument":"create","updateDocument":"update"},"PostNext":{"type":"PostNext","resolveType":"multiCollectionDocument","createDocument":"create","updateDocument":"update"},"Post":{"type":"Post","resolveType":"collectionDocument","collection":"post","createPost":"create","updatePost":"update"},"PostConnection":{"type":"PostConnection","resolveType":"collectionDocumentList","collection":"post"},"Abtest":{"type":"Abtest","resolveType":"collectionDocument","collection":"abtest","createAbtest":"create","updateAbtest":"update"},"AbtestConnection":{"type":"AbtestConnection","resolveType":"collectionDocumentList","collection":"abtest"}}